{
  "need_update" : false,
  "high_schools": [
    {
      "name": "パワフル高校",
      "before_events": 31,
      "after_events": 39
    },
    {
      "name": "パワフル高校(限定)",
      "before_events": 32,
      "after_events": 41
    },
    {
      "name": "瞬鋭高校",
      "before_events": 35,
      "after_events": 43
    },
    {
      "name": "瞬鋭高校(限定)",
      "before_events": 36,
      "after_events": 39
    }
  ],
  "event_characters": [
    {
      "name": "青葉春人（SR）",
      "rarity": "SR",
      "before_events": 1,
      "after_events": 0
    },
    {
      "name": "秋葉一真（SR）",
      "rarity": "SR",
      "before_events": 2,
      "after_events": 0
    },
    {
      "name": "明星雪華（SR）",
      "rarity": "SR",
      "before_events": 3,
      "after_events": 0
    },
    {
      "name": "阿畑やすし（SR）",
      "rarity": "SR",
      "before_events": 0,
      "after_events": 1
    },
    {
      "name": "天城隼（SR）",
      "rarity": "SR",
      "before_events": 0,
      "after_events": 2
    },
    {
      "name": "嵐丸士朗（SR）",
      "rarity": "SR",
      "before_events": 0,
      "after_events": 3
    }
  ]
}
